[
  {
    "quoteText": "To be or not to be",
    "source": "Hamlet",
    "sourceMedium": "PLAY"
  },
  {
    "quoteText": "As you wish.",
    "source": "The Princess Bride",
    "sourceMedium": "MOVIE"
  },
  {
    "quoteText": "Have fun stoming the castle!",
    "source": "The Princess Bride",
    "sourceMedium": "MOVIE"
  },
  {
    "quoteText": "Never go up against a Sicilian when DEATH is on the line!",
    "source": "The Princess Bride",
    "sourceMedium": "MOVIE"
  },
  {
    "quoteText": "You keep using that word. I do not think it means what you think it means.",
    "source": "The Princess Bride",
    "sourceMedium": "MOVIE"
  },
  {
    "quoteText": "Life is pain. Anyone who says different is trying to sell you something.",
    "source": "The Princess Bride",
    "sourceMedium": "MOVIE"
  },
  {
    "quoteText": "You're trying to kidnap what I've rightfully stolen.",
    "source": "The Princess Bride",
    "sourceMedium": "MOVIE"
  },
  {
    "quoteText": "I'll explain, and I'll use small words so that you'll be sure to understand, you warthog-faced baboon.",
    "source": "The Princess Bride",
    "sourceMedium": "MOVIE"
  },
  {
    "quoteText": "You rush a miracle man, you get rotten miracles.",
    "source": "The Princess Bride",
    "sourceMedium": "MOVIE"
  },
  {
    "quoteText": "He is only MOSTLY dead.",
    "source": "The Princess Bride",
    "sourceMedium": "MOVIE"
  },
  {
    "quoteText": "Have fun storming the castle!",
    "source": "The Princess Bride",
    "sourceMedium": "MOVIE"
  },
  {
    "quoteText": "You ARE the Brute Squad!",
    "source": "The Princess Bride",
    "sourceMedium": "MOVIE"
  }
]
